{"gtabs":[{"panes":[{"ptabs":[{"history":[{"dir":"/home/maxmya","file":"Downloads","relpos":1,"ts":1762177488},{"dir":"/home/maxmya/Downloads","file":"..","relpos":0,"ts":1762177488},{"dir":"/home/maxmya","file":"Downloads","relpos":1,"ts":1762177488},{"dir":"/home/maxmya/Downloads","file":"..","relpos":0,"ts":1762177488},{"dir":"/home/maxmya","file":"dotfiles","relpos":3,"ts":1762177488},{"dir":"/home/maxmya/dotfiles","file":"..","relpos":0,"ts":1762177488},{"dir":"/home/maxmya","file":"dotfiles","relpos":3,"ts":1762177488},{"dir":"/home/maxmya/dotfiles","file":"..","relpos":0,"ts":1762177488},{"dir":"/home/maxmya","file":"dotfiles","relpos":3,"ts":1762177488},{"dir":"/home","file":"maxmya","relpos":1,"ts":1762177488},{"dir":"/","file":"home","relpos":4,"ts":1762177488},{"dir":"/home","file":"maxmya","relpos":1,"ts":1762177488},{"dir":"/home/maxmya","file":"Playground","relpos":2,"ts":1762177488},{"dir":"/home/maxmya/Playground","file":"yay-bin","relpos":1,"ts":1762177488},{"dir":"/home/maxmya/Playground/yay-bin","file":"..","relpos":0,"ts":1762177488},{"dir":"/home/maxmya/Playground","file":"..","relpos":0,"ts":1762177488},{"dir":"/home/maxmya","file":"dotfiles","relpos":3,"ts":1762177488},{"dir":"/home/maxmya/dotfiles","file":"..","relpos":0,"ts":1762177488},{"dir":"/home/maxmya","file":"dotfiles","relpos":3,"ts":1762177488},{"dir":"/home/maxmya/dotfiles","file":"..","relpos":0,"ts":1762177488},{"dir":"/home/maxmya","file":"Playground","relpos":2,"ts":1762177488},{"dir":"/home/maxmya/Playground","file":"..","relpos":0,"ts":1762177488}],"filters":{"invert":true,"dot":true,"manual":"","auto":""},"last-location":"/home/maxmya/Playground","sorting":[2],"preview":false}]},{"ptabs":[{"history":[{"dir":"/home/maxmya","file":"..","relpos":0,"ts":1762177488}],"filters":{"invert":true,"dot":true,"manual":"","auto":""},"last-location":"/home/maxmya","sorting":[2],"preview":false}]}],"active-pane":1,"preview":false,"splitter":{"pos":-1,"ratio":0.5,"orientation":"v","expanded":false}}],"active-gtab":0,"marks":{"H":{"dir":"/home/maxmya/","file":"..","ts":1762177434},"b":{"dir":"/home/maxmya/bin/","file":"..","ts":1762177434},"h":{"dir":"/home/maxmya/","file":"..","ts":1762177434},"z":{"dir":"/home/maxmya/.config/vifm","file":"..","ts":1762177434}},"bmarks":{},"cmd-hist":[{"text":"q","ts":1762177488}],"regs":{},"dir-stack":[],"use-term-multiplexer":false}